Metadata-Version: 2.1
Name: razortrace
Version: 0.1
Summary: Straight forward memory leak detection
Home-page: https://github.com/manbehindthemadness/razortrace
Author: manbehindthemadness
Author-email: manbehindthemadness@gmail.com
License: MIT
Keywords: malloc,memory,leak,trace
Platform: UNKNOWN
License-File: LICENSE
